Workbook

Sheet Dashboard
B2: FUND MANAGEMENT & RECONCILIATION
B3: FY2025 Multi-Fund Portfolio · 8 Active Funds · Monthly Bank Reconciliation
B5: TOTAL FUNDS UNDER MGMT | E5: YTD EXPENDITURES | G5: CURRENT BALANCE | I5: RECONCILIATION STATUS
B6: =E20 -> 5520000 | E6: =G20 -> 2453048 | G6: =H20 -> 6436952 | I6: =IF(SUMPRODUCT(--(Reconciliation!G5:G16<>0))=0,"ALL CLEAN","REVIEW") -> ALL CLEAN
B7: 8 active funds · FY2025 | E7: All outflows · to date | G7: After inflows & outflows | I7: 12 of 12 months · zero variance
B10: FUND BALANCES SUMMARY
B11: Code | C11: Fund Name | D11: Category | E11: Opening Balance | F11: Inflows (YTD) | G11: Outflows (YTD) | H11: Current Balance | I11: Utilization | J11: Status
B12: GF-001 | C12: General Operating Fund | D12: State | E12: 1250000 | F12: =SUMIFS(Transactions!F:F,Transactions!C:C,B12,Transactions!E:E,"Inflow") -> 668000 | G12: =SUMIFS(Transactions!F:F,Transactions!C:C,B12,Transactions!E:E,"Outflow") -> 315548 | H12: =E12+F12-G12 -> 1602452 | I12: =IFERROR(G12/E12,0) -> 0.2524384 | J12: =IF(I12>1,"Over Budget",IF(I12>0.85,"Review",IF(I12>0.6,"Monitor","On Track"))) -> On Track
B13: FG-204 | C13: Federal Grant - Community Dev | D13: Federal | E13: 850000 | F13: =SUMIFS(Transactions!F:F,Transactions!C:C,B13,Transactions!E:E,"Inflow") -> 370000 | G13: =SUMIFS(Transactions!F:F,Transactions!C:C,B13,Transactions!E:E,"Outflow") -> 368229 | H13: =E13+F13-G13 -> 851771 | I13: =IFERROR(G13/E13,0) -> 0.43321059 | J13: =IF(I13>1,"Over Budget",IF(I13>0.85,"Review",IF(I13>0.6,"Monitor","On Track"))) -> On Track
B14: FG-315 | C14: Federal Grant - Workforce Initiative | D14: Federal | E14: 620000 | F14: =SUMIFS(Transactions!F:F,Transactions!C:C,B14,Transactions!E:E,"Inflow") -> 260000 | G14: =SUMIFS(Transactions!F:F,Transactions!C:C,B14,Transactions!E:E,"Outflow") -> 275434 | H14: =E14+F14-G14 -> 604566 | I14: =IFERROR(G14/E14,0) -> 0.44424839 | J14: =IF(I14>1,"Over Budget",IF(I14>0.85,"Review",IF(I14>0.6,"Monitor","On Track"))) -> On Track
B15: TR-101 | C15: Governor's Office Travel Fund | D15: State | E15: 185000 | F15: =SUMIFS(Transactions!F:F,Transactions!C:C,B15,Transactions!E:E,"Inflow") -> 115000 | G15: =SUMIFS(Transactions!F:F,Transactions!C:C,B15,Transactions!E:E,"Outflow") -> 36476 | H15: =E15+F15-G15 -> 263524 | I15: =IFERROR(G15/E15,0) -> 0.19716757 | J15: =IF(I15>1,"Over Budget",IF(I15>0.85,"Review",IF(I15>0.6,"Monitor","On Track"))) -> On Track
B16: EV-050 | C16: Annual Stakeholder Event Fund | D16: Event | E16: 60000 | F16: =SUMIFS(Transactions!F:F,Transactions!C:C,B16,Transactions!E:E,"Inflow") -> 67000 | G16: =SUMIFS(Transactions!F:F,Transactions!C:C,B16,Transactions!E:E,"Outflow") -> 96803 | H16: =E16+F16-G16 -> 30197 | I16: =IFERROR(G16/E16,0) -> 1.6133833 | J16: =IF(I16>1,"Over Budget",IF(I16>0.85,"Review",IF(I16>0.6,"Monitor","On Track"))) -> Over Budget
B17: CM-440 | C17: Capital Maintenance Fund | D17: State | E17: 425000 | F17: =SUMIFS(Transactions!F:F,Transactions!C:C,B17,Transactions!E:E,"Inflow") -> 195000 | G17: =SUMIFS(Transactions!F:F,Transactions!C:C,B17,Transactions!E:E,"Outflow") -> 132688 | H17: =E17+F17-G17 -> 487312 | I17: =IFERROR(G17/E17,0) -> 0.31220706 | J17: =IF(I17>1,"Over Budget",IF(I17>0.85,"Review",IF(I17>0.6,"Monitor","On Track"))) -> On Track
B18: SG-112 | C18: Subgrantee Pass-Through Fund | D18: Federal | E18: 1150000 | F18: =SUMIFS(Transactions!F:F,Transactions!C:C,B18,Transactions!E:E,"Inflow") -> 1140000 | G18: =SUMIFS(Transactions!F:F,Transactions!C:C,B18,Transactions!E:E,"Outflow") -> 899738 | H18: =E18+F18-G18 -> 1390262 | I18: =IFERROR(G18/E18,0) -> 0.78238087 | J18: =IF(I18>1,"Over Budget",IF(I18>0.85,"Review",IF(I18>0.6,"Monitor","On Track"))) -> Monitor
B19: OP-220 | C19: Agency Operations Fund | D19: State | E19: 980000 | F19: =SUMIFS(Transactions!F:F,Transactions!C:C,B19,Transactions!E:E,"Inflow") -> 555000 | G19: =SUMIFS(Transactions!F:F,Transactions!C:C,B19,Transactions!E:E,"Outflow") -> 328132 | H19: =E19+F19-G19 -> 1206868 | I19: =IFERROR(G19/E19,0) -> 0.33482857 | J19: =IF(I19>1,"Over Budget",IF(I19>0.85,"Review",IF(I19>0.6,"Monitor","On Track"))) -> On Track
B20: TOTAL | E20: =SUM(E12:E19) -> 5520000 | F20: =SUM(F12:F19) -> 3370000 | G20: =SUM(G12:G19) -> 2453048 | H20: =SUM(H12:H19) -> 6436952 | I20: =IFERROR(G20/E20,0) -> 0.44439275 | J20: =IF(I20>1,"Over","OK") -> OK
B23: CONTROLS & NOTES
B24: ▸ All fund balances are reconciled monthly against AZ360 State Accounting System ledger entries.
B25: ▸ Utilization color scale: light green (healthy) → amber (caution >70%) → light red (review >100%).
B26: ▸ Federal fund drawdowns processed via ACH in compliance with 2 CFR 200 and SAAM guidance.
B27: ▸ Inflows and outflows pull dynamically from the Transactions ledger via SUMIFS — no manual updates.
B29: Illustrative portfolio model · Figures are synthesized to demonstrate workflow and do not represent actual State of Arizona financial records.
B30: Prepared by Thomas P. McCoy · Senior Accountant & Grant Auditor · Modeled on multi-fund state accounting operations

Sheet Fund Register
B1: FUND REGISTER — Master list of all fund codes, categories, and authorization details
B3: Code | C3: Fund Name | D3: Category | E3: FY Start | F3: FY End | G3: Budget Authority | H3: Status | I3: Manager
B4: GF-001 | C4: General Operating Fund | D4: State | E4: 45474 | F4: 45838 | G4: 1250000 | H4: Active | I4: T. McCoy
B5: FG-204 | C5: Federal Grant - Community Dev | D5: Federal | E5: 45566 | F5: 45930 | G5: 850000 | H5: Active | I5: T. McCoy
B6: FG-315 | C6: Federal Grant - Workforce Initiative | D6: Federal | E6: 45566 | F6: 45930 | G6: 620000 | H6: Active | I6: T. McCoy
B7: TR-101 | C7: Governor's Office Travel Fund | D7: State | E7: 45474 | F7: 45838 | G7: 185000 | H7: Active | I7: T. McCoy
B8: EV-050 | C8: Annual Stakeholder Event Fund | D8: Event | E8: 45474 | F8: 45838 | G8: 60000 | H8: Active | I8: T. McCoy
B9: CM-440 | C9: Capital Maintenance Fund | D9: State | E9: 45474 | F9: 45838 | G9: 425000 | H9: Active | I9: T. McCoy
B10: SG-112 | C10: Subgrantee Pass-Through Fund | D10: Federal | E10: 45566 | F10: 45930 | G10: 1150000 | H10: Active | I10: T. McCoy
B11: OP-220 | C11: Agency Operations Fund | D11: State | E11: 45474 | F11: 45838 | G11: 980000 | H11: Active | I11: T. McCoy
B14: Illustrative portfolio model · Figures are synthesized to demonstrate workflow and do not represent actual State of Arizona financial records.

Sheet Transactions
B1: TRANSACTIONS LEDGER — All FY2025 fund activity tied to Fund Codes for SUMIFS aggregation
B3: Date | C3: Fund Code | D3: Description | E3: Type | F3: Amount | G3: Category | H3: Vendor/Source | I3: GL Account
B4: 45672 | C4: FG-204 | D4: Program Materials | E4: Outflow | F4: 18365 | G4: Program Materials | H4: Print Pro | I4: 7020-Materials
B5: 45672 | C5: FG-315 | D5: Federal Drawdown | E5: Inflow | F5: 75000 | G5: Federal Drawdown | H5: US Treasury | I5: 4100-Fed Draw
B6: 45672 | C6: GF-001 | D6: State Appropriation | E6: Inflow | F6: 125000 | G6: State Appropriation | H6: State Treasurer | I6: 4010-Approp
B7: 45685 | C7: CM-440 | D7: Facility Repair | E7: Outflow | F7: 13776 | G7: Facility Repair | H7: Johnson Controls | I7: 5610-Repair
B8: 45685 | C8: CM-440 | D8: Facility Repair | E8: Outflow | F8: 31441 | G8: Facility Repair | H8: Johnson Controls | I8: 5610-Repair
B9: 45685 | C9: EV-050 | D9: Sponsor Revenue | E9: Inflow | F9: 12000 | G9: Sponsor Revenue | H9: Sponsor Partners | I9: 4040-Sponsor
B10: 45685 | C10: EV-050 | D10: Venue Rental | E10: Outflow | F10: 11506 | G10: Venue Rental | H10: Phoenix Convention Ctr | I10: 5510-Venue
B11: 45685 | C11: EV-050 | D11: Venue Rental | E11: Outflow | F11: 8060 | G11: Venue Rental | H11: Phoenix Convention Ctr | I11: 5510-Venue
B12: 45685 | C12: GF-001 | D12: Fee Revenue | E12: Inflow | F12: 88000 | G12: Fee Revenue | H12: Various | I12: 4020-Fees
B13: 45685 | C13: SG-112 | D13: Federal Drawdown | E13: Inflow | F13: 290000 | G13: Federal Drawdown | H13: US Treasury | I13: 4100-Fed Draw
B14: 45698 | C14: EV-050 | D14: Registration Revenue | E14: Inflow | F14: 15000 | G14: Registration Revenue | H14: Attendees | I14: 4030-Event Rev
B15: 45698 | C15: EV-050 | D15: Catering | E15: Outflow | F15: 8379 | G15: Catering | H15: Cateria Catering | I15: 5520-Catering
... B143: 45951 | C143: TR-101 | D143: Lodging | E143: Outflow | F143: 2658 | G143: Lodging | H143: Hilton | I143: 5420-Travel Lodging
B144: INFLOWS TOTAL (140 transactions) | F144: =SUMIFS(F4:F143,E4:E143,"Inflow") -> 3370000
B145: OUTFLOWS TOTAL | F145: =SUMIFS(F4:F143,E4:E143,"Outflow") -> 2453048
B146: NET POSITION | F146: =F144-F145 -> 916952
B148: Illustrative portfolio model · Figures are synthesized to demonstrate workflow and do not represent actual State of Arizona financial records.

Sheet Reconciliation
B1: MONTHLY BANK RECONCILIATION — Bank Statement vs. General Ledger
B2: Formula: Variance = (Bank Balance + Deposits in Transit − Outstanding Checks) − GL Balance. Target = $0.00
B4: Month | C4: Bank Balance | D4: GL Balance | E4: Deposits in Transit | F4: Outstanding Checks | G4: Variance | H4: Status | I4: Notes
B5: January 2025 | C5: 4285420 | D5: 4325120 | E5: 45200 | F5: 5500 | G5: =(C5+E5-F5)-D5 -> 0 | H5: =IF(ABS(G5)<=100,"Reconciled","Review") -> Reconciled | I5: All items cleared by M+3
B6: February 2025 | C6: 4512880 | D6: 4548650 | E6: 38770 | F6: 3000 | G6: =(C6+E6-F6)-D6 -> 0 | H6: =IF(ABS(G6)<=100,"Reconciled","Review") -> Reconciled | I6: Clean reconciliation
B7: March 2025 | C7: 4728105 | D7: 4765890 | E7: 42785 | F7: 5000 | G7: =(C7+E7-F7)-D7 -> 0 | H7: =IF(ABS(G7)<=100,"Reconciled","Review") -> Reconciled | I7: Q1 close completed on schedule
B8: April 2025 | C8: 4950220 | D8: 4982940 | E8: 35720 | F8: 3000 | G8: =(C8+E8-F8)-D8 -> 0 | H8: =IF(ABS(G8)<=100,"Reconciled","Review") -> Reconciled | I8: Travel accruals adjusted
B9: May 2025 | C9: 5120885 | D9: 5168335 | E9: 49450 | F9: 2000 | G9: =(C9+E9-F9)-D9 -> 0 | H9: =IF(ABS(G9)<=100,"Reconciled","Review") -> Reconciled | I9: Federal drawdown timing normalized
B10: June 2025 | C10: 5315440 | D10: 5360740 | E10: 48300 | F10: 3000 | G10: =(C10+E10-F10)-D10 -> 0 | H10: =IF(ABS(G10)<=100,"Reconciled","Review") -> Reconciled | I10: FY close — zero unadjusted variance
B11: July 2025 | C11: 5498220 | D11: 5541610 | E11: 46390 | F11: 3000 | G11: =(C11+E11-F11)-D11 -> 0 | H11: =IF(ABS(G11)<=100,"Reconciled","Review") -> Reconciled | I11: FY26 opening cycle
B12: August 2025 | C12: 5680150 | D12: 5719450 | E12: 42300 | F12: 3000 | G12: =(C12+E12-F12)-D12 -> 0 | H12: =IF(ABS(G12)<=100,"Reconciled","Review") -> Reconciled | I12: Clean recon
B13: September 2025 | C13: 5845910 | D13: 5883560 | E13: 40650 | F13: 3000 | G13: =(C13+E13-F13)-D13 -> 0 | H13: =IF(ABS(G13)<=100,"Reconciled","Review") -> Reconciled | I13: Federal FY close complete
B14: October 2025 | C14: 5990280 | D14: 6026430 | E14: 39150 | F14: 3000 | G14: =(C14+E14-F14)-D14 -> 0 | H14: =IF(ABS(G14)<=100,"Reconciled","Review") -> Reconciled | I14: All items traced
B15: November 2025 | C15: 6120450 | D15: 6157260 | E15: 39810 | F15: 3000 | G15: =(C15+E15-F15)-D15 -> 0 | H15: =IF(ABS(G15)<=100,"Reconciled","Review") -> Reconciled | I15: Budget carryover booked
B16: December 2025 | C16: 6288920 | D16: 6328290 | E16: 42370 | F16: 3000 | G16: =(C16+E16-F16)-D16 -> 0 | H16: =IF(ABS(G16)<=100,"Reconciled","Review") -> Reconciled | I16: YE close — zero variance
B17: TOTAL | C17: =SUM(C5:C16) -> 64336880 | D17: =SUM(D5:D16) -> 64808275 | E17: =SUM(E5:E16) -> 510895 | F17: =SUM(F5:F16) -> 39500 | G17: =SUM(G5:G16) -> 0 | H17: Clean | I17: 12 of 12 months reconciled
B19: RECONCILIATION METHODOLOGY
B20: 1. Pull bank statement balance at month-end from treasury portal (JP Morgan Gov't Banking).
B21: 2. Extract GL balance from AZ360 State Accounting System — Fund-level trial balance.
B22: 3. Identify timing differences: deposits in transit + outstanding checks + adjusting entries.
B23: 4. Variance calculation: (Bank + DIT − OC) − GL. Target = $0.00.
B24: 5. Document exceptions and resolve within 3 business days of month-end close.
B26: Illustrative portfolio model · Figures are synthesized to demonstrate workflow and do not represent actual State of Arizona financial records.

Sheet Pivot Summary
B1: EXPENDITURE ANALYSIS — Pivot-style summaries via SUMIFS, refresh-free
B3: OUTFLOWS BY FUND | H3: OUTFLOWS BY FUND CATEGORY
B4: Fund | C4: Outflows | D4: % of Total | E4: Budget Authority | F4: Remaining | H4: Category | I4: Outflows | J4: % of Total
B5: GF-001 — General Operating Fund | C5: =SUMIFS(Transactions!F:F,Transactions!C:C,"GF-001",Transactions!E:E,"Outflow") -> 315548 | D5: =IFERROR(C5/C$13,0) -> 0.12863507 | E5: 1250000 | F5: =E5-C5 -> 934452 | H5: State | I5: =SUMIFS(Transactions!F:F,Transactions!C:C,"GF-001",Transactions!E:E,"Outflow")+SUMIFS(Transactions!F:F,Transactions!C:C,"TR-101",Transactions!E:E,"Outflow")+SUMIFS(Transactions!F:F,Transactions!C:C,"CM-440",Transactions!E:E,"Outflow")+SUMIFS(Transactions!F:F,Transactions!C:C,"OP-220",Transactions!E:E,"Outflow") -> 812844 | J5: =IFERROR(I5/I$8,0) -> 0.33136082
B6: FG-204 — Federal Grant - Community Dev | C6: =SUMIFS(Transactions!F:F,Transactions!C:C,"FG-204",Transactions!E:E,"Outflow") -> 368229 | D6: =IFERROR(C6/C$13,0) -> 0.1501108 | E6: 850000 | F6: =E6-C6 -> 481771 | H6: Federal | I6: =SUMIFS(Transactions!F:F,Transactions!C:C,"FG-204",Transactions!E:E,"Outflow")+SUMIFS(Transactions!F:F,Transactions!C:C,"FG-315",Transactions!E:E,"Outflow")+SUMIFS(Transactions!F:F,Transactions!C:C,"SG-112",Transactions!E:E,"Outflow") -> 1543401 | J6: =IFERROR(I6/I$8,0) -> 0.62917684
B7: FG-315 — Federal Grant - Workforce Initiative | C7: =SUMIFS(Transactions!F:F,Transactions!C:C,"FG-315",Transactions!E:E,"Outflow") -> 275434 | D7: =IFERROR(C7/C$13,0) -> 0.11228235 | E7: 620000 | F7: =E7-C7 -> 344566 | H7: Event | I7: =SUMIFS(Transactions!F:F,Transactions!C:C,"EV-050",Transactions!E:E,"Outflow") -> 96803 | J7: =IFERROR(I7/I$8,0) -> 0.039462334
B8: TR-101 — Governor's Office Travel Fund | C8: =SUMIFS(Transactions!F:F,Transactions!C:C,"TR-101",Transactions!E:E,"Outflow") -> 36476 | D8: =IFERROR(C8/C$13,0) -> 0.014869664 | E8: 185000 | F8: =E8-C8 -> 148524 | H8: TOTAL | I8: =SUM(I5:I7) -> 2453048 | J8: 100.0%
B9: EV-050 — Annual Stakeholder Event Fund | C9: =SUMIFS(Transactions!F:F,Transactions!C:C,"EV-050",Transactions!E:E,"Outflow") -> 96803 | D9: =IFERROR(C9/C$13,0) -> 0.039462334 | E9: 60000 | F9: =E9-C9 -> -36803
B10: CM-440 — Capital Maintenance Fund | C10: =SUMIFS(Transactions!F:F,Transactions!C:C,"CM-440",Transactions!E:E,"Outflow") -> 132688 | D10: =IFERROR(C10/C$13,0) -> 0.054091074 | E10: 425000 | F10: =E10-C10 -> 292312
B11: SG-112 — Subgrantee Pass-Through Fund | C11: =SUMIFS(Transactions!F:F,Transactions!C:C,"SG-112",Transactions!E:E,"Outflow") -> 899738 | D11: =IFERROR(C11/C$13,0) -> 0.36678369 | E11: 1150000 | F11: =E11-C11 -> 250262
B12: OP-220 — Agency Operations Fund | C12: =SUMIFS(Transactions!F:F,Transactions!C:C,"OP-220",Transactions!E:E,"Outflow") -> 328132 | D12: =IFERROR(C12/C$13,0) -> 0.13376501 | E12: 980000 | F12: =E12-C12 -> 651868
B13: TOTAL | C13: =SUM(C5:C12) -> 2453048 | D13: 100.0% | E13: =SUM(E5:E12) -> 5520000 | F13: =E13-C13 -> 3066952
B16: Illustrative portfolio model · Figures are synthesized to demonstrate workflow and do not represent actual State of Arizona financial records.

Sheet _ChartData
A1: Fund | B1: Inflows | C1: Outflows | E1: Category | F1: Outflows | H1: Month | I1: Inflows | J1: Outflows | K1: Net | M1: Month | N1: Variance
A2: GF-001 | B2: =Dashboard!F12 -> 668000 | C2: =Dashboard!G12 -> 315548 | E2: State | F2: ='Pivot Summary'!I5 -> 812844 | H2: Jan | I2: =SUMIFS(Transactions!F:F,Transactions!B:B,">="&DATE(2025,1,1),Transactions!B:B,"<"&DATE(2025,1+1,1),Transactions!E:E,"Inflow") -> 590000 | J2: =SUMIFS(Transactions!F:F,Transactions!B:B,">="&DATE(2025,1,1),Transactions!B:B,"<"&DATE(2025,1+1,1),Transactions!E:E,"Outflow") -> 83148 | K2: =I2-J2 -> 506852 | M2: =Reconciliation!B5 -> January 2025 | N2: =Reconciliation!G5 -> 0
A3: FG-204 | B3: =Dashboard!F13 -> 370000 | C3: =Dashboard!G13 -> 368229 | E3: Federal | F3: ='Pivot Summary'!I6 -> 1543401 | H3: Feb | I3: =SUMIFS(Transactions!F:F,Transactions!B:B,">="&DATE(2025,2,1),Transactions!B:B,"<"&DATE(2025,2+1,1),Transactions!E:E,"Inflow") -> 122000 | J3: =SUMIFS(Transactions!F:F,Transactions!B:B,">="&DATE(2025,2,1),Transactions!B:B,"<"&DATE(2025,2+1,1),Transactions!E:E,"Outflow") -> 263697 | K3: =I3-J3 -> -141697 | M3: =Reconciliation!B6 -> February 2025 | N3: =Reconciliation!G6 -> 0
A4: FG-315 | B4: =Dashboard!F14 -> 260000 | C4: =Dashboard!G14 -> 275434 | E4: Event | F4: ='Pivot Summary'!I7 -> 96803 | H4: Mar | I4: =SUMIFS(Transactions!F:F,Transactions!B:B,">="&DATE(2025,3,1),Transactions!B:B,"<"&DATE(2025,3+1,1),Transactions!E:E,"Inflow") -> 280000 | J4: =SUMIFS(Transactions!F:F,Transactions!B:B,">="&DATE(2025,3,1),Transactions!B:B,"<"&DATE(2025,3+1,1),Transactions!E:E,"Outflow") -> 333053 | K4: =I4-J4 -> -53053 | M4: =Reconciliation!B7 -> March 2025 | N4: =Reconciliation!G7 -> 0
A5: TR-101 | B5: =Dashboard!F15 -> 115000 | C5: =Dashboard!G15 -> 36476 | H5: Apr | I5: =SUMIFS(Transactions!F:F,Transactions!B:B,">="&DATE(2025,4,1),Transactions!B:B,"<"&DATE(2025,4+1,1),Transactions!E:E,"Inflow") -> 372000 | J5: =SUMIFS(Transactions!F:F,Transactions!B:B,">="&DATE(2025,4,1),Transactions!B:B,"<"&DATE(2025,4+1,1),Transactions!E:E,"Outflow") -> 465443 | K5: =I5-J5 -> -93443 | M5: =Reconciliation!B8 -> April 2025 | N5: =Reconciliation!G8 -> 0
A6: EV-050 | B6: =Dashboard!F16 -> 67000 | C6: =Dashboard!G16 -> 96803 | H6: May | I6: =SUMIFS(Transactions!F:F,Transactions!B:B,">="&DATE(2025,5,1),Transactions!B:B,"<"&DATE(2025,5+1,1),Transactions!E:E,"Inflow") -> 213000 | J6: =SUMIFS(Transactions!F:F,Transactions!B:B,">="&DATE(2025,5,1),Transactions!B:B,"<"&DATE(2025,5+1,1),Transactions!E:E,"Outflow") -> 245411 | K6: =I6-J6 -> -32411 | M6: =Reconciliation!B9 -> May 2025 | N6: =Reconciliation!G9 -> 0
A7: CM-440 | B7: =Dashboard!F17 -> 195000 | C7: =Dashboard!G17 -> 132688 | H7: Jun | I7: =SUMIFS(Transactions!F:F,Transactions!B:B,">="&DATE(2025,6,1),Transactions!B:B,"<"&DATE(2025,6+1,1),Transactions!E:E,"Inflow") -> 310000 | J7: =SUMIFS(Transactions!F:F,Transactions!B:B,">="&DATE(2025,6,1),Transactions!B:B,"<"&DATE(2025,6+1,1),Transactions!E:E,"Outflow") -> 113723 | K7: =I7-J7 -> 196277 | M7: =Reconciliation!B10 -> June 2025 | N7: =Reconciliation!G10 -> 0
A8: SG-112 | B8: =Dashboard!F18 -> 1140000 | C8: =Dashboard!G18 -> 899738 | H8: Jul | I8: =SUMIFS(Transactions!F:F,Transactions!B:B,">="&DATE(2025,7,1),Transactions!B:B,"<"&DATE(2025,7+1,1),Transactions!E:E,"Inflow") -> 0 | J8: =SUMIFS(Transactions!F:F,Transactions!B:B,">="&DATE(2025,7,1),Transactions!B:B,"<"&DATE(2025,7+1,1),Transactions!E:E,"Outflow") -> 109065 | K8: =I8-J8 -> -109065 | M8: =Reconciliation!B11 -> July 2025 | N8: =Reconciliation!G11 -> 0
A9: OP-220 | B9: =Dashboard!F19 -> 555000 | C9: =Dashboard!G19 -> 328132 | H9: Aug | I9: =SUMIFS(Transactions!F:F,Transactions!B:B,">="&DATE(2025,8,1),Transactions!B:B,"<"&DATE(2025,8+1,1),Transactions!E:E,"Inflow") -> 703000 | J9: =SUMIFS(Transactions!F:F,Transactions!B:B,">="&DATE(2025,8,1),Transactions!B:B,"<"&DATE(2025,8+1,1),Transactions!E:E,"Outflow") -> 357830 | K9: =I9-J9 -> 345170 | M9: =Reconciliation!B12 -> August 2025 | N9: =Reconciliation!G12 -> 0
H10: Sep | I10: =SUMIFS(Transactions!F:F,Transactions!B:B,">="&DATE(2025,9,1),Transactions!B:B,"<"&DATE(2025,9+1,1),Transactions!E:E,"Inflow") -> 395000 | J10: =SUMIFS(Transactions!F:F,Transactions!B:B,">="&DATE(2025,9,1),Transactions!B:B,"<"&DATE(2025,9+1,1),Transactions!E:E,"Outflow") -> 395413 | K10: =I10-J10 -> -413 | M10: =Reconciliation!B13 -> September 2025 | N10: =Reconciliation!G13 -> 0
H11: Oct | I11: =SUMIFS(Transactions!F:F,Transactions!B:B,">="&DATE(2025,10,1),Transactions!B:B,"<"&DATE(2025,10+1,1),Transactions!E:E,"Inflow") -> 385000 | J11: =SUMIFS(Transactions!F:F,Transactions!B:B,">="&DATE(2025,10,1),Transactions!B:B,"<"&DATE(2025,10+1,1),Transactions!E:E,"Outflow") -> 86265 | K11: =I11-J11 -> 298735 | M11: =Reconciliation!B14 -> October 2025 | N11: =Reconciliation!G14 -> 0
H12: Nov | I12: =SUMIFS(Transactions!F:F,Transactions!B:B,">="&DATE(2025,11,1),Transactions!B:B,"<"&DATE(2025,11+1,1),Transactions!E:E,"Inflow") -> 0 | J12: =SUMIFS(Transactions!F:F,Transactions!B:B,">="&DATE(2025,11,1),Transactions!B:B,"<"&DATE(2025,11+1,1),Transactions!E:E,"Outflow") -> 0 | K12: =I12-J12 -> 0 | M12: =Reconciliation!B15 -> November 2025 | N12: =Reconciliation!G15 -> 0
H13: Dec | I13: =SUMIFS(Transactions!F:F,Transactions!B:B,">="&DATE(2025,12,1),Transactions!B:B,"<"&DATE(2025,12+1,1),Transactions!E:E,"Inflow") -> 0 | J13: =SUMIFS(Transactions!F:F,Transactions!B:B,">="&DATE(2025,12,1),Transactions!B:B,"<"&DATE(2025,12+1,1),Transactions!E:E,"Outflow") -> 0 | K13: =I13-J13 -> 0 | M13: =Reconciliation!B16 -> December 2025 | N13: =Reconciliation!G16 -> 0

Sheet Charts
B2: VISUAL ANALYSIS — Fund Management & Reconciliation FY2025
B3: Six views using a WCAG-AA colorblind-safe palette (blue/orange primary pairing)
B5: § 01 · FUND-LEVEL ACTIVITY
B27: § 02 · MONTHLY CASH FLOW & NET POSITION
B49: § 03 · FUND UTILIZATION & RECONCILIATION PERFORMANCE
B71: § 04 · KEY INSIGHTS
B73: ▸ $5.52M managed across 8 funds — State, Federal, and Event — with zero reconciliation variances across all 12 months.
B74: ▸ Federal fund activity (Community Dev, Workforce Initiative, Subgrantee) represents the largest spending category at ~63% of total outflows.
B75: ▸ EV-050 Event Fund flags 161% utilization (Over Budget) — drove the FY4 turnaround case study; SG-112 at 78% requires monitoring.
B76: ▸ Monthly net cash flow pattern: surplus in Q1 and Q3 offsets Q2 drawdown timing — useful for FY26 cash-position forecasting.
B77: ▸ All charts use a colorblind-safe palette (blue/orange pairing) meeting WCAG-AA contrast standards for accessibility.
B80: Illustrative portfolio model · Figures are synthesized to demonstrate workflow and do not represent actual State of Arizona financial records.

Sheet Features Used
B1: FEATURES & METHODOLOGY
B2: A walkthrough of the Excel features, formulas, and design choices powering this workbook.
B4: Sheet / Area | C4: Feature Used | D4: What It Does & Why It Matters | E4: Business Impact
B5: Dashboard — KPI Cards | C5: Formula-Driven KPIs | D5: Every KPI card (Total Funds, YTD Expenditures, Current Balance, Reconciliation Status) pulls from table formulas — not hardcoded. Change a transaction and every card updates instantly. | E5: Eliminates manual refresh · audit-ready accuracy
B6: Dashboard — Fund Balances | C6: SUMIFS Aggregation | D6: Inflows and Outflows columns use SUMIFS with fund-code + transaction-type criteria. Pulls dynamically from the Transactions ledger without any pivot refreshes. | E6: Real-time aggregation across 140+ transactions
B7: Dashboard — Utilization % | C7: Color Scale Conditional Formatting | D7: 3-color gradient (green → amber → red) applied to Utilization column. Hiring managers see which funds are over/under spend at a glance. | E7: Data at a glance · faster exception ID
B8: Dashboard — Status Column | C8: Nested IF Logic + CF Rules | D8: Status = IF(util>100%, "Over Budget", IF(util>85%, "Review", IF(util>60%, "Monitor", "On Track"))). Each status triggers a distinct colorblind-safe cell fill. | E8: Automated risk tiering · consistent thresholds
B9: Transactions — Totals | C9: SUMIFS by Transaction Type | D9: Footer splits totals into Inflows, Outflows, and Net Position separately — SUMIFS filters by the Type column. Prevents the common accounting error of summing all amounts as one. | E9: Eliminates mis-summation risk
B10: Reconciliation | C10: Variance Formula | D10: Variance = (Bank Balance + Deposits in Transit − Outstanding Checks) − GL Balance. Calculates the 4-point recon equation automatically for each of 12 months. | E10: Standardized GL-to-bank tie-out
B11: Reconciliation — Status | C11: IF with ABS Tolerance | D11: Status flags "Reconciled" if |variance| ≤ $100, else "Review". Tolerance threshold documented in the methodology block. | E11: Auto-flags exceptions for M+3 resolution
B12: Pivot Summary | C12: SUMIFS Pivot Alternative | D12: Replicates Excel PivotTable aggregation using SUMIFS — no manual refreshes needed. Totals by Fund AND by Fund Category side-by-side. | E12: Formula-driven pivots never go stale
B13: Pivot Summary — Remaining | C13: Data Bar Conditional Formatting | D13: Data bars on Remaining column create an instant visual of which funds have the most/least headroom. | E13: Visual comparison without reading numbers
B14: Charts Sheet | C14: Colorblind-Safe Palette | D14: All 6 charts use the Paul Tol / IBM Design qualitative palette — blue/orange primary pairing is distinguishable under deuteranopia, protanopia, and tritanopia. | E14: WCAG-AA accessibility · reaches all reviewers
B15: Charts — Cash Flow Bars | C15: Per-Point Color Logic | D15: Monthly Net Cash Flow bars individually colored — green for surplus months, orange for deficit. Line-item color coding inside a single chart series. | E15: Pattern emerges visually · no reading required
... B21: Formulas | C21: IFERROR Wrappers | D21: Division formulas (Utilization, % of Total) wrapped in IFERROR to gracefully handle any zero-denominator scenarios without breaking the dashboard. | E21: Graceful error handling · robust to edge cases
B24: Illustrative portfolio model · Figures are synthesized to demonstrate workflow and do not represent actual State of Arizona financial records.
B25: Prepared by Thomas P. McCoy · Senior Accountant & Grant Auditor · The Ledger, Vol. I — Edition 02
