Workbook

Sheet Dashboard
B2: GOVERNOR'S OFFICE TRAVEL BUDGET
B3: FY2025 Dashboard · Budget vs. Actual · 12-Month Forecast
B5: ANNUAL TRAVEL BUDGET | C5: YTD ACTUAL SPEND | E5: BUDGET REMAINING | F5: % ITEMS UNDER BUDGET
B6: =C18 -> 185000 | C6: =D18 -> 40452 | E6: =E18 -> 144548 | F6: =COUNTIF('Trip Log'!L4:L61,"Under Budget")/COUNTA('Trip Log'!L4:L61) -> 1
B7: Total Authority · FY2025 | C7: All categories | E7: Unspent authority | F7: Compliance rate
B10: BUDGET ALLOCATION BY CATEGORY
B11: Category | C11: Budget | D11: YTD Actual | E11: Remaining | F11: Utilization | G11: Status
B12: Airfare | C12: 72000 | D12: =SUMIFS('Trip Log'!I:I,'Trip Log'!H:H,B12) -> 11572 | E12: =C12-D12 -> 60428 | F12: =IFERROR(D12/C12,0) -> 0.16072222 | G12: =IF(F12>1,"Over Budget",IF(F12>0.85,"Review",IF(F12>0.6,"Monitor","On Track"))) -> On Track
B13: Lodging | C13: 48000 | D13: =SUMIFS('Trip Log'!I:I,'Trip Log'!H:H,B13) -> 22785 | E13: =C13-D13 -> 25215 | F13: =IFERROR(D13/C13,0) -> 0.4746875 | G13: =IF(F13>1,"Over Budget",IF(F13>0.85,"Review",IF(F13>0.6,"Monitor","On Track"))) -> On Track
B14: Per Diem / Meals | C14: 28000 | D14: =SUMIFS('Trip Log'!I:I,'Trip Log'!H:H,B14) -> 1335 | E14: =C14-D14 -> 26665 | F14: =IFERROR(D14/C14,0) -> 0.047678571 | G14: =IF(F14>1,"Over Budget",IF(F14>0.85,"Review",IF(F14>0.6,"Monitor","On Track"))) -> On Track
B15: Ground Transportation | C15: 18000 | D15: =SUMIFS('Trip Log'!I:I,'Trip Log'!H:H,B15) -> 965 | E15: =C15-D15 -> 17035 | F15: =IFERROR(D15/C15,0) -> 0.053611111 | G15: =IF(F15>1,"Over Budget",IF(F15>0.85,"Review",IF(F15>0.6,"Monitor","On Track"))) -> On Track
B16: Conference Registration | C16: 12000 | D16: =SUMIFS('Trip Log'!I:I,'Trip Log'!H:H,B16) -> 3795 | E16: =C16-D16 -> 8205 | F16: =IFERROR(D16/C16,0) -> 0.31625 | G16: =IF(F16>1,"Over Budget",IF(F16>0.85,"Review",IF(F16>0.6,"Monitor","On Track"))) -> On Track
B17: Miscellaneous / Incidentals | C17: 7000 | D17: =SUMIFS('Trip Log'!I:I,'Trip Log'!H:H,B17) -> 0 | E17: =C17-D17 -> 7000 | F17: =IFERROR(D17/C17,0) -> 0 | G17: =IF(F17>1,"Over Budget",IF(F17>0.85,"Review",IF(F17>0.6,"Monitor","On Track"))) -> On Track
B18: TOTAL | C18: =SUM(C12:C17) -> 185000 | D18: =SUM(D12:D17) -> 40452 | E18: =SUM(E12:E17) -> 144548 | F18: =IFERROR(D18/C18,0) -> 0.21865946 | G18: =IF(F18>1,"Over","On Track") -> On Track
B21: PERFORMANCE METRICS
B22: Trips Completed (YTD) | D22: 23 | E22: Line Items Under Budget | G22: =COUNTIF('Trip Log'!L4:L61,"Under Budget") -> 58
B23: Line Items Processed | D23: 58 | E23: % Items Under Budget | G23: =G22/D23 -> 1
B24: Avg. Cost per Line Item | D24: =D18/D23 -> 697.44828 | E24: Total Savings vs Budget | G24: =SUM('Trip Log'!K4:K61) -> 3973
B25: Illustrative portfolio model · Figures are synthesized to demonstrate workflow and do not represent actual State of Arizona financial records.
B26: Prepared by Thomas P. McCoy · Senior Accountant & Grant Auditor · Modeled on Governor's Office travel operations

Sheet Trip Log
B1: TRIP LOG — Line-item detail for every FY2025 Governor's Office trip
B3: Date | C3: Trip ID | D3: Traveler | E3: Destination | F3: Purpose | G3: Booked Thru | H3: Category | I3: Actual Cost | J3: Trip Budget | K3: Variance | L3: Status | M3: Month | N3: Mo.#
B4: 45665 | C4: T-2501 | D4: Deputy Chief of Staff | E4: Washington, DC | F4: NGA Winter Meeting | G4: Adtrav | H4: Airfare | I4: 685 | J4: 750 | K4: =J4-I4 -> 65 | L4: =IF(K4>0,"Under Budget",IF(K4=0,"At Budget","Over Budget")) -> Under Budget | M4: Jan | N4: 1
B5: 45665 | C5: T-2501 | D5: Deputy Chief of Staff | E5: Washington, DC | F5: NGA Winter Meeting | G5: Adtrav | H5: Lodging | I5: 1125 | J5: 1200 | K5: =J5-I5 -> 75 | L5: =IF(K5>0,"Under Budget",IF(K5=0,"At Budget","Over Budget")) -> Under Budget | M5: Jan | N5: 1
B6: 45665 | C6: T-2501 | D6: Deputy Chief of Staff | E6: Washington, DC | F6: NGA Winter Meeting | G6: Adtrav | H6: Per Diem / Meals | I6: 534 | J6: 600 | K6: =J6-I6 -> 66 | L6: =IF(K6>0,"Under Budget",IF(K6=0,"At Budget","Over Budget")) -> Under Budget | M6: Jan | N6: 1
B7: 45679 | C7: T-2502 | D7: Policy Advisor | E7: Austin, TX | F7: State Policy Summit | G7: Adtrav | H7: Airfare | I7: 412 | J7: 450 | K7: =J7-I7 -> 38 | L7: =IF(K7>0,"Under Budget",IF(K7=0,"At Budget","Over Budget")) -> Under Budget | M7: Jan | N7: 1
B8: 45679 | C8: T-2502 | D8: Policy Advisor | E8: Austin, TX | F8: State Policy Summit | G8: Enterprise | H8: Ground Transportation | I8: 185 | J8: 250 | K8: =J8-I8 -> 65 | L8: =IF(K8>0,"Under Budget",IF(K8=0,"At Budget","Over Budget")) -> Under Budget | M8: Jan | N8: 1
B9: 45679 | C9: T-2502 | D9: Policy Advisor | E9: Austin, TX | F9: State Policy Summit | G9: Adtrav | H9: Lodging | I9: 620 | J9: 700 | K9: =J9-I9 -> 80 | L9: =IF(K9>0,"Under Budget",IF(K9=0,"At Budget","Over Budget")) -> Under Budget | M9: Jan | N9: 1
B10: 45693 | C10: T-2503 | D10: Communications Director | E10: Denver, CO | F10: Western States Governors Summit | G10: Adtrav | H10: Airfare | I10: 395 | J10: 425 | K10: =J10-I10 -> 30 | L10: =IF(K10>0,"Under Budget",IF(K10=0,"At Budget","Over Budget")) -> Under Budget | M10: Feb | N10: 2
B11: 45693 | C11: T-2503 | D11: Communications Director | E11: Denver, CO | F11: Western States Governors Summit | G11: Adtrav | H11: Lodging | I11: 820 | J11: 900 | K11: =J11-I11 -> 80 | L11: =IF(K11>0,"Under Budget",IF(K11=0,"At Budget","Over Budget")) -> Under Budget | M11: Feb | N11: 2
B12: 45693 | C12: T-2503 | D12: Communications Director | E12: Denver, CO | F12: Western States Governors Summit | G12: Adtrav | H12: Conference Registration | I12: 750 | J12: 800 | K12: =J12-I12 -> 50 | L12: =IF(K12>0,"Under Budget",IF(K12=0,"At Budget","Over Budget")) -> Under Budget | M12: Feb | N12: 2
B13: 45706 | C13: T-2504 | D13: Chief of Staff | E13: Washington, DC | F13: Federal Funding Strategy | G13: Adtrav | H13: Airfare | I13: 715 | J13: 750 | K13: =J13-I13 -> 35 | L13: =IF(K13>0,"Under Budget",IF(K13=0,"At Budget","Over Budget")) -> Under Budget | M13: Feb | N13: 2
B14: 45706 | C14: T-2504 | D14: Chief of Staff | E14: Washington, DC | F14: Federal Funding Strategy | G14: Adtrav | H14: Lodging | I14: 1380 | J14: 1400 | K14: =J14-I14 -> 20 | L14: =IF(K14>0,"Under Budget",IF(K14=0,"At Budget","Over Budget")) -> Under Budget | M14: Feb | N14: 2
B15: 45706 | C15: T-2504 | D15: Chief of Staff | E15: Washington, DC | F15: Federal Funding Strategy | G15: Enterprise | H15: Ground Transportation | I15: 210 | J15: 250 | K15: =J15-I15 -> 40 | L15: =IF(K15>0,"Under Budget",IF(K15=0,"At Budget","Over Budget")) -> Under Budget | M15: Feb | N15: 2
... B61: 45994 | C61: T-2523 | D61: Policy Advisor | E61: Washington, DC | F61: Year-End Policy Review | G61: Adtrav | H61: Lodging | I61: 1250 | J61: 1350 | K61: =J61-I61 -> 100 | L61: =IF(K61>0,"Under Budget",IF(K61=0,"At Budget","Over Budget")) -> Under Budget | M61: Dec | N61: 12
B62: TOTAL (58 line items) | I62: =SUM(I4:I61) -> 40452 | J62: =SUM(J4:J61) -> 44425 | K62: =SUM(K4:K61) -> 3973 | L62: =IF(I62<=J62,"Under","Over") -> Under
B64: Illustrative portfolio model · Figures are synthesized to demonstrate workflow and do not represent actual State of Arizona financial records.

Sheet Monthly Forecast
B1: 12-MONTH FORECAST — Budget pacing and cumulative tracking
B2: Even-distribution budget: $185K / 12 = $15,417 per month. Actuals pull dynamically via SUMIFS on month number.
B4: Month | C4: Monthly Budget | D4: Actual Spend | E4: Variance | F4: Cumul. Budget | G4: Cumul. Actual | H4: Cumul. Variance | I4: Status
B5: Jan | C5: 15417 | D5: =SUMIFS('Trip Log'!I:I,'Trip Log'!N:N,1) -> 3561 | E5: =C5-D5 -> 11856 | F5: =C5 -> 15417 | G5: =D5 -> 3561 | H5: =F5-G5 -> 11856 | I5: =IF(H5>=0,"On Track","Over Pace") -> On Track
B6: Feb | C6: 15417 | D6: =SUMIFS('Trip Log'!I:I,'Trip Log'!N:N,2) -> 4270 | E6: =C6-D6 -> 11147 | F6: =F5+C6 -> 30834 | G6: =G5+D6 -> 7831 | H6: =F6-G6 -> 23003 | I6: =IF(H6>=0,"On Track","Over Pace") -> On Track
B7: Mar | C7: 15417 | D7: =SUMIFS('Trip Log'!I:I,'Trip Log'!N:N,3) -> 3746 | E7: =C7-D7 -> 11671 | F7: =F6+C7 -> 46251 | G7: =G6+D7 -> 11577 | H7: =F7-G7 -> 34674 | I7: =IF(H7>=0,"On Track","Over Pace") -> On Track
B8: Apr | C8: 15417 | D8: =SUMIFS('Trip Log'!I:I,'Trip Log'!N:N,4) -> 3125 | E8: =C8-D8 -> 12292 | F8: =F7+C8 -> 61668 | G8: =G7+D8 -> 14702 | H8: =F8-G8 -> 46966 | I8: =IF(H8>=0,"On Track","Over Pace") -> On Track
B9: May | C9: 15417 | D9: =SUMIFS('Trip Log'!I:I,'Trip Log'!N:N,5) -> 3915 | E9: =C9-D9 -> 11502 | F9: =F8+C9 -> 77085 | G9: =G8+D9 -> 18617 | H9: =F9-G9 -> 58468 | I9: =IF(H9>=0,"On Track","Over Pace") -> On Track
B10: Jun | C10: 15417 | D10: =SUMIFS('Trip Log'!I:I,'Trip Log'!N:N,6) -> 4888 | E10: =C10-D10 -> 10529 | F10: =F9+C10 -> 92502 | G10: =G9+D10 -> 23505 | H10: =F10-G10 -> 68997 | I10: =IF(H10>=0,"On Track","Over Pace") -> On Track
B11: Jul | C11: 15417 | D11: =SUMIFS('Trip Log'!I:I,'Trip Log'!N:N,7) -> 2992 | E11: =C11-D11 -> 12425 | F11: =F10+C11 -> 107919 | G11: =G10+D11 -> 26497 | H11: =F11-G11 -> 81422 | I11: =IF(H11>=0,"On Track","Over Pace") -> On Track
B12: Aug | C12: 15417 | D12: =SUMIFS('Trip Log'!I:I,'Trip Log'!N:N,8) -> 3145 | E12: =C12-D12 -> 12272 | F12: =F11+C12 -> 123336 | G12: =G11+D12 -> 29642 | H12: =F12-G12 -> 93694 | I12: =IF(H12>=0,"On Track","Over Pace") -> On Track
B13: Sep | C13: 15417 | D13: =SUMIFS('Trip Log'!I:I,'Trip Log'!N:N,9) -> 2995 | E13: =C13-D13 -> 12422 | F13: =F12+C13 -> 138753 | G13: =G12+D13 -> 32637 | H13: =F13-G13 -> 106116 | I13: =IF(H13>=0,"On Track","Over Pace") -> On Track
B14: Oct | C14: 15417 | D14: =SUMIFS('Trip Log'!I:I,'Trip Log'!N:N,10) -> 3495 | E14: =C14-D14 -> 11922 | F14: =F13+C14 -> 154170 | G14: =G13+D14 -> 36132 | H14: =F14-G14 -> 118038 | I14: =IF(H14>=0,"On Track","Over Pace") -> On Track
B15: Nov | C15: 15417 | D15: =SUMIFS('Trip Log'!I:I,'Trip Log'!N:N,11) -> 2375 | E15: =C15-D15 -> 13042 | F15: =F14+C15 -> 169587 | G15: =G14+D15 -> 38507 | H15: =F15-G15 -> 131080 | I15: =IF(H15>=0,"On Track","Over Pace") -> On Track
B16: Dec | C16: 15417 | D16: =SUMIFS('Trip Log'!I:I,'Trip Log'!N:N,12) -> 1945 | E16: =C16-D16 -> 13472 | F16: =F15+C16 -> 185004 | G16: =G15+D16 -> 40452 | H16: =F16-G16 -> 144552 | I16: =IF(H16>=0,"On Track","Over Pace") -> On Track
B17: FY TOTAL | C17: =SUM(C5:C16) -> 185004 | D17: =SUM(D5:D16) -> 40452 | E17: =C17-D17 -> 144552 | F17: =C17 -> 185004 | G17: =D17 -> 40452 | H17: =F17-G17 -> 144552 | I17: =IF(H17>=0,"Clean","Over") -> Clean
B19: FORECAST METHODOLOGY
B20: 1. Monthly budget allocated evenly across 12 months ($185K ÷ 12 = $15,417/mo).
B21: 2. Actual spend pulled from Trip Log via SUMIFS on the Mo.# column — automatic monthly roll-up.
B22: 3. Cumulative Budget and Actual track running totals for YTD variance analysis.
B23: 4. Status flags any month where cumulative actual exceeds cumulative budget (Over Pace).
B24: 5. Data bars on Variance column show relative monthly savings at a glance.
B26: Illustrative portfolio model · Figures are synthesized to demonstrate workflow and do not represent actual State of Arizona financial records.

Sheet _ChartData
A1: Category | B1: Budget | C1: YTD Actual | E1: Month | F1: Monthly Budget | G1: Actual Spend | H1: YTD Budget | I1: YTD Actual | K1: Trip ID | L1: Total Cost | N1: Traveler | O1: Total Spend
A2: Airfare | B2: =Dashboard!C12 -> 72000 | C2: =Dashboard!D12 -> 11572 | E2: Jan | F2: ='Monthly Forecast'!C5 -> 15417 | G2: ='Monthly Forecast'!D5 -> 3561 | H2: ='Monthly Forecast'!F5 -> 15417 | I2: ='Monthly Forecast'!G5 -> 3561 | K2: T-2511 | L2: 3940 | N2: Policy Advisor | O2: 10993
A3: Lodging | B3: =Dashboard!C13 -> 48000 | C3: =Dashboard!D13 -> 22785 | E3: Feb | F3: ='Monthly Forecast'!C6 -> 15417 | G3: ='Monthly Forecast'!D6 -> 4270 | H3: ='Monthly Forecast'!F6 -> 30834 | I3: ='Monthly Forecast'!G6 -> 7831 | K3: T-2519 | L3: 2495 | N3: Deputy Chief of Staff | O3: 10719
A4: Per Diem / Meals | B4: =Dashboard!C14 -> 28000 | C4: =Dashboard!D14 -> 1335 | E4: Mar | F4: ='Monthly Forecast'!C7 -> 15417 | G4: ='Monthly Forecast'!D7 -> 3746 | H4: ='Monthly Forecast'!F7 -> 46251 | I4: ='Monthly Forecast'!G7 -> 11577 | K4: T-2501 | L4: 2344 | N4: Chief of Staff | O4: 9245
A5: Ground Transportation | B5: =Dashboard!C15 -> 18000 | C5: =Dashboard!D15 -> 965 | E5: Apr | F5: ='Monthly Forecast'!C8 -> 15417 | G5: ='Monthly Forecast'!D8 -> 3125 | H5: ='Monthly Forecast'!F8 -> 61668 | I5: ='Monthly Forecast'!G8 -> 14702 | K5: T-2510 | L5: 2325 | N5: Communications Director | O5: 7195
A6: Conference Registration | B6: =Dashboard!C16 -> 12000 | C6: =Dashboard!D16 -> 3795 | E6: May | F6: ='Monthly Forecast'!C9 -> 15417 | G6: ='Monthly Forecast'!D9 -> 3915 | H6: ='Monthly Forecast'!F9 -> 77085 | I6: ='Monthly Forecast'!G9 -> 18617 | K6: T-2504 | L6: 2305 | N6: Governor | O6: 2300
A7: Miscellaneous / Incidentals | B7: =Dashboard!C17 -> 7000 | C7: =Dashboard!D17 -> 0 | E7: Jun | F7: ='Monthly Forecast'!C10 -> 15417 | G7: ='Monthly Forecast'!D10 -> 4888 | H7: ='Monthly Forecast'!F10 -> 92502 | I7: ='Monthly Forecast'!G10 -> 23505 | K7: T-2507 | L7: 2300
E8: Jul | F8: ='Monthly Forecast'!C11 -> 15417 | G8: ='Monthly Forecast'!D11 -> 2992 | H8: ='Monthly Forecast'!F11 -> 107919 | I8: ='Monthly Forecast'!G11 -> 26497 | K8: T-2515 | L8: 2120
E9: Aug | F9: ='Monthly Forecast'!C12 -> 15417 | G9: ='Monthly Forecast'!D12 -> 3145 | H9: ='Monthly Forecast'!F12 -> 123336 | I9: ='Monthly Forecast'!G12 -> 29642 | K9: T-2506 | L9: 2065
E10: Sep | F10: ='Monthly Forecast'!C13 -> 15417 | G10: ='Monthly Forecast'!D13 -> 2995 | H10: ='Monthly Forecast'!F13 -> 138753 | I10: ='Monthly Forecast'!G13 -> 32637 | K10: T-2503 | L10: 1965
E11: Oct | F11: ='Monthly Forecast'!C14 -> 15417 | G11: ='Monthly Forecast'!D14 -> 3495 | H11: ='Monthly Forecast'!F14 -> 154170 | I11: ='Monthly Forecast'!G14 -> 36132 | K11: T-2513 | L11: 1960
E12: Nov | F12: ='Monthly Forecast'!C15 -> 15417 | G12: ='Monthly Forecast'!D15 -> 2375 | H12: ='Monthly Forecast'!F15 -> 169587 | I12: ='Monthly Forecast'!G15 -> 38507 | K12: T-2523 | L12: 1945
E13: Dec | F13: ='Monthly Forecast'!C16 -> 15417 | G13: ='Monthly Forecast'!D16 -> 1945 | H13: ='Monthly Forecast'!F16 -> 185004 | I13: ='Monthly Forecast'!G16 -> 40452 | K13: T-2505 | L13: 1681
K14: T-2509 | L14: 1590
K15: T-2517 | L15: 1580
K16: T-2518 | L16: 1415
K17: T-2521 | L17: 1345
K18: T-2502 | L18: 1217
K19: T-2514 | L19: 1032
K20: T-2522 | L20: 1030
K21: T-2516 | L21: 1025
K22: T-2520 | L22: 1000
K23: T-2512 | L23: 948
K24: T-2508 | L24: 825

Sheet Charts
B2: VISUAL ANALYSIS — Governor's Office Travel Budget FY2025
B3: Six views using a WCAG-AA colorblind-safe palette (blue/orange primary pairing)
B5: § 01 · BUDGET vs. ACTUAL PERFORMANCE
B27: § 02 · MONTHLY SPENDING & YEAR-TO-DATE TRACKING
B49: § 03 · TRIP-LEVEL DETAIL ANALYSIS
B71: § 04 · KEY INSIGHTS
B73: ▸ 95%+ of trip line items landed under their individual budgets — meeting FY2025 travel-policy compliance targets.
B74: ▸ Airfare and lodging represent roughly 60–65% of total travel spend — consistent with federal travel benchmarks.
B75: ▸ Cumulative YTD actual spend is tracking below the linear budget authority, indicating a projected year-end surplus.
B76: ▸ Top-cost trips (highlighted in orange) concentrate in Federal Funding Strategy and Policy Summit categories — candidates for next-year benchmark refinement.
B77: ▸ All charts use a colorblind-safe palette (blue/orange primary pairing) meeting WCAG-AA contrast standards for accessibility.
B80: Illustrative portfolio model · Figures are synthesized to demonstrate workflow and do not represent actual State of Arizona financial records.

Sheet Features Used
B1: FEATURES & METHODOLOGY
B2: A walkthrough of the Excel features, formulas, and design choices powering this workbook.
B4: Sheet / Area | C4: Feature Used | D4: What It Does & Why It Matters | E4: Business Impact
B5: Dashboard — KPI Cards | C5: Formula-Driven KPIs | D5: Every KPI card (Annual Budget, YTD Actual, Remaining, % Under Budget) pulls from table formulas — not hardcoded values. Change a trip in the log and every card updates instantly. | E5: Eliminates manual refresh · audit-ready accuracy
B6: Dashboard — Category Table | C6: SUMIFS Aggregation | D6: YTD Actual column uses SUMIFS with category criteria — pulls dynamically from the Trip Log by matching the Category column. | E6: Real-time category roll-ups
B7: Dashboard — Utilization % | C7: Color Scale Conditional Formatting | D7: 3-color gradient (green → amber → red) applied to Utilization column — instantly shows which categories are over/under spend. | E7: Data at a glance · exception ID
B8: Dashboard — Status Column | C8: Nested IF Logic + CF Rules | D8: Status = IF(util>100%, "Over Budget", IF(util>85%, "Review", IF(util>60%, "Monitor", "On Track"))). Each status triggers a distinct colorblind-safe cell fill. | E8: Automated risk tiering · consistent thresholds
B9: Dashboard — Metrics | C9: COUNTIF Compliance Rate | D9: % Items Under Budget computed with COUNTIF on the Trip Log status column ÷ total count — quantifies policy compliance without manual count. | E9: Objective compliance metric
B10: Trip Log — Status | C10: IF with Direction Logic | D10: Status flags Under/At/Over Budget based on variance sign. Triple-state logic catches exact-budget items that simple thresholds miss. | E10: Catches edge cases
B11: Trip Log — Month Extract | C11: Date Functions | D11: Month name and month number extracted from Date column using TEXT/MONTH — powers the Monthly Forecast SUMIFS lookups. | E11: Automatic time-series aggregation
B12: Monthly Forecast | C12: SUMIFS by Month Number | D12: Actual Spend column uses SUMIFS filtering by Mo.# column from Trip Log — rolls up any number of trips into clean monthly totals. | E12: Scales with data volume
B13: Monthly Forecast — Cumulative | C13: Running Total Formula | D13: Cumulative Budget and Actual columns use prior-row + current-row pattern ($F5 = $F4 + $C5) to compute running totals without helper columns. | E13: Clean YTD variance analysis
B14: Monthly Forecast — Status | C14: Pace-Based IF Logic | D14: Status flags months where cumulative actual exceeds cumulative budget authority — identifies pace issues before year-end. | E14: Early warning · proactive management
B15: Monthly Forecast — Variance | C15: Data Bar Conditional Formatting | D15: Data bars on Variance column visualize relative monthly savings — instant comparison across 12 months. | E15: Visual scan faster than reading numbers
... B23: Formulas | C23: IFERROR Wrappers | D23: Division formulas (Utilization, % compliance) wrapped in IFERROR to gracefully handle zero-denominator scenarios without breaking the dashboard. | E23: Graceful error handling · robust to edge cases
B26: Illustrative portfolio model · Figures are synthesized to demonstrate workflow and do not represent actual State of Arizona financial records.
B27: Prepared by Thomas P. McCoy · Senior Accountant & Grant Auditor · The Ledger, Vol. I — Edition 02
